{"url": "https://developer.blender.org/people/manage/158846", "phid": "PHID-USER-oemdlbq2wsfeimvcfuns", "username": "Kiteliving"}
{"url": "https://developer.blender.org/people/manage/158914", "phid": "PHID-USER-kx57r4mqabvrnitanhgp", "username": "EmmaJackson2711"}
{"url": "https://developer.blender.org/people/manage/158645", "phid": "PHID-USER-4orrnvc6oveqrgdkkieq", "username": "MarcoHoo"}
{"url": "https://developer.blender.org/people/manage/158917", "phid": "PHID-USER-2xcayvvlq6ut4l2jaami", "username": "jessicabyrne11"}
{"url": "https://developer.blender.org/people/manage/158924", "phid": "PHID-USER-q7hporsp5lpvuvyli4xs", "username": "starmkgunu"}
{"url": "https://developer.blender.org/people/manage/158923", "phid": "PHID-USER-25h4bc6nbe4awwq4ts6o", "username": "Strudelbrain"}
{"url": "https://developer.blender.org/people/manage/158918", "phid": "PHID-USER-wqmeffjjcuxnqc6its5h", "username": "pandoza-vg168"}
 
