{"url": "https://developer.blender.org/people/manage/159416", "phid": "PHID-USER-dckshmupaemr3amzpf36", "username": "ronanwarner97"}
{"url": "https://developer.blender.org/people/manage/159414", "phid": "PHID-USER-ripr7opfadxzsiogb6pp", "username": "Freeonlineslots"}
{"url": "https://developer.blender.org/people/manage/159426", "phid": "PHID-USER-ebdvecxt3to2q6ckwpyr", "username": "LuckyDragon94"}
{"url": "https://developer.blender.org/people/manage/159430", "phid": "PHID-USER-bje5hm57xivv25chpiio", "username": "markstark072"}
{"url": "https://developer.blender.org/people/manage/159443", "phid": "PHID-USER-kjxdqmcewnyyrludx2ss", "username": "tavernier01"}
{"url": "https://developer.blender.org/people/manage/155604", "phid": "PHID-USER-au562k2ehffhwlv5ukck", "username": "PratikPB2123"}
{"url": "https://developer.blender.org/people/manage/159445", "phid": "PHID-USER-t2amhq2hmkmg47wln7on", "username": "amitkhanna85"}
{"url": "https://developer.blender.org/people/manage/159450", "phid": "PHID-USER-v6cpkp2uipapjrob5v2n", "username": "cemsid"}
{"url": "https://developer.blender.org/people/manage/128717", "phid": "PHID-USER-m7cfnsftjknuahbkm7so", "username": "nomade040"}
{"url": "https://developer.blender.org/people/manage/159452", "phid": "PHID-USER-zej3xq5a7e5qblfan5xj", "username": "vadehi"}
{"url": "https://developer.blender.org/people/manage/159465", "phid": "PHID-USER-qasahgpchk7hgaeins6u", "username": "getprocrack"}
{"url": "https://developer.blender.org/people/manage/159470", "phid": "PHID-USER-f7rndp3ivgqxjqt6zvng", "username": "alex71"}
{"url": "https://developer.blender.org/people/manage/159489", "phid": "PHID-USER-w6nm7bjoutg3uiib3fwt", "username": "veri"}
{"url": "https://developer.blender.org/people/manage/159506", "phid": "PHID-USER-oftoii2gljuehlrgrojm", "username": "ahmetsait"}
{"url": "https://developer.blender.org/people/manage/159519", "phid": "PHID-USER-2ojnr4pmbc2nb6rwyk2z", "username": "alekspodolan"}
{"url": "https://developer.blender.org/people/manage/159535", "phid": "PHID-USER-x5tpwfhkoiqlu64w74d7", "username": "OfficeCleaningMelbourne"}
{"url": "https://developer.blender.org/people/manage/153409", "phid": "PHID-USER-qs325aa2jnic6syowlcg", "username": "Ghostkeeper"}
{"url": "https://developer.blender.org/people/manage/132636", "phid": "PHID-USER-6w75ee75xnm4ikdneykq", "username": "jmztn"}
{"url": "https://developer.blender.org/people/manage/159573", "phid": "PHID-USER-x45e4xc5x2bzgktku4d4", "username": "samanthasteves9"}
{"url": "https://developer.blender.org/people/manage/159590", "phid": "PHID-USER-xb23vhdut6tzmwwfvkxw", "username": "onlinecasino"}
{"url": "https://developer.blender.org/people/manage/145566", "phid": "PHID-USER-hymlq5hcjdr776oxqy3w", "username": "0000"}
{"url": "https://developer.blender.org/people/manage/159604", "phid": "PHID-USER-hfomo7tgadd4vjynedkt", "username": "Libertex"}
{"url": "https://developer.blender.org/people/manage/159603", "phid": "PHID-USER-m3gj7siphuzunsxdrh2h", "username": "bestevpn"}
{"url": "https://developer.blender.org/people/manage/159605", "phid": "PHID-USER-bgpl57sthudi5ypajxuf", "username": "boekhoudprogramma"}
{"url": "https://developer.blender.org/people/manage/159619", "phid": "PHID-USER-wr7ra5jw6pqrxm26eife", "username": "Strike_Digital"}
{"url": "https://developer.blender.org/people/manage/144544", "phid": "PHID-USER-vgisnge3oku4hbblpys5", "username": "Panel_to_panel"}
{"url": "https://developer.blender.org/people/manage/159634", "phid": "PHID-USER-n53mwbu2sb2gpdslzjo4", "username": "engineeringcollege"}
{"url": "https://developer.blender.org/people/manage/159638", "phid": "PHID-USER-rhnvvjzr6jtxfemqpr6n", "username": "alexowe8130"}
{"url": "https://developer.blender.org/people/manage/159641", "phid": "PHID-USER-icuofd42m5raga2scerh", "username": "websitecenter"}
{"url": "https://developer.blender.org/people/manage/159643", "phid": "PHID-USER-e2unfrwqik43rhxcde5h", "username": "certsagent"}
{"url": "https://developer.blender.org/people/manage/159646", "phid": "PHID-USER-h3fwnr244b4oxkldlp23", "username": "drpaulsfds"}
{"url": "https://developer.blender.org/people/manage/159652", "phid": "PHID-USER-pnkzdr5v33vollqc4235", "username": "FloorPolishingGeelong"}
{"url": "https://developer.blender.org/people/manage/135361", "phid": "PHID-USER-b2lqvqgoel47zymx6u3m", "username": "kenziemac130"}
{"url": "https://developer.blender.org/people/manage/156114", "phid": "PHID-USER-5xrwsfyowtnvqatn3qve", "username": "aaka"}
{"url": "https://developer.blender.org/people/manage/159654", "phid": "PHID-USER-grmj22er47jc333och6n", "username": "williamjames"}
{"url": "https://developer.blender.org/people/manage/159659", "phid": "PHID-USER-k2zj3ya3erswobxwa2yy", "username": "Gfreya860"}
{"url": "https://developer.blender.org/people/manage/159678", "phid": "PHID-USER-527ok7bttyja6vqx6uwi", "username": "martineromy940"}
{"url": "https://developer.blender.org/people/manage/159682", "phid": "PHID-USER-p5oozsjjtgrfhl5jyk6l", "username": "Delhirentcar"}
{"url": "https://developer.blender.org/people/manage/159683", "phid": "PHID-USER-zzubpwihx6yhfyfiok7p", "username": "LOQIStore"}
{"url": "https://developer.blender.org/people/manage/159686", "phid": "PHID-USER-nqiv3hie4qer2ctkfafc", "username": "arabellagross"}
{"url": "https://developer.blender.org/people/manage/159707", "phid": "PHID-USER-7urijebnzdl7iqkhbuox", "username": "AgentA1cr"}
{"url": "https://developer.blender.org/people/manage/159708", "phid": "PHID-USER-dt2nejkcuuwjuhjqzxar", "username": "Huasomuerto"}
{"url": "https://developer.blender.org/people/manage/134368", "phid": "PHID-USER-q6xecc2vczgvz4im6sps", "username": "d-egg"}
{"url": "https://developer.blender.org/people/manage/159717", "phid": "PHID-USER-ay3pmhsv5j2yqr7euan5", "username": "IndianMatka"}
{"url": "https://developer.blender.org/people/manage/159716", "phid": "PHID-USER-znd3ex5mimyqsqm6jfbj", "username": "essencestudios2d"}
{"url": "https://developer.blender.org/people/manage/159725", "phid": "PHID-USER-duzx4de6772wv2cybtgw", "username": "tekwire"}
{"url": "https://developer.blender.org/people/manage/159723", "phid": "PHID-USER-lbkaktehf3ut2yrydxcc", "username": "aoitechsolutionsbbb"}
{"url": "https://developer.blender.org/people/manage/138020", "phid": "PHID-USER-mzzs75hxobnhfkmhjcvj", "username": "Squesh"}
{"url": "https://developer.blender.org/people/manage/159730", "phid": "PHID-USER-oolnecssmzv6avjuhxbj", "username": "fegongroup"}
{"url": "https://developer.blender.org/people/manage/159728", "phid": "PHID-USER-q6im4gjewxtnblwc6c66", "username": "wireitsolutions"}
{"url": "https://developer.blender.org/people/manage/159755", "phid": "PHID-USER-dlltojip7qvzta7qnjsp", "username": "Best-Banquet-Hall-in-Surat"}
 
